<?xml version="1.0" encoding="utf-8"?><?xml-stylesheet type="text/xsl" href="styles.xsl" ?><text><body>
         <p>
<hi rend="b">[179]</hi>
         </p>
         <p>
<hi rend="b">Wednesday, May 13</hi><hi rend="b sup u">th</hi><hi rend="b">, 1903.</hi>
         </p>
         <p><persName id="371">M<hi rend="sup u">r</hi> Howland</persName> &amp; his stenographer (a lady) arrived, &amp; for about 20 minutes I dictated my opinions on the Anti-rate campaign of the sectaries.<note id="101" n="1">  Then I attended the <orgName id="68">Convocation</orgName>, &amp; sat there all the morning.  <hi rend="i b u"><persName id="376">Canon Knox Little</persName> handed in notice of a <term id="7">gravamen</term> calling upon the Bps. to make a declaration with respect to the Virgin Birth &amp;c</hi>. If this comes on for discussion, I shall have to defend myself.</p>
         <p>There lunched here</p>
         <p><persName id="381">Bishop of Coventry</persName></p>
         <p><persName id="382">Dean of Windsor</persName></p>
         <p><persName id="285">" " Peterboro</persName></p>
         <p><persName id="378">" " S. Alban's</persName></p>
         <p><persName id="383">Archdeacon Spooner</persName></p>
         <p><persName id="68">Canon Pereira</persName></p>
         <p><persName id="384">Prebendary Ingram</persName></p>
         <p><persName id="350">Canon Thompson</persName></p>
         <p>
            
         </p>
         </body></text>
