<?xml version="1.0" encoding="utf-8"?><?xml-stylesheet type="text/xsl" href="styles.xsl" ?><text><body>
         <p>
<hi rend="b">[334]</hi>
         </p>
         <p>
<hi rend="b">11</hi><hi rend="b sup u">th</hi><hi rend="b"> Sunday after Trinity, August 14</hi><hi rend="b sup u">th</hi><hi rend="b">, 1904</hi>.</p>
         <p>There was a large congregation at 10 a.m. when I <event id="126">preached</event> in the Abbey on the Responsibility of Privilege.  The collection of the <orgName id="157">Children's Country Holiday Fund</orgName> exceeded &#x00A3;41.</p>
         <p>I preached again in the afternoon, &amp; - although the weather had become rainy - there was again a large congregation.  Offertory nearly &#x00A3;23.</p>
         </body></text>
